openweathermapapi/__init__.py
openweathermapapi/api_helper.py
openweathermapapi/configuration.py
openweathermapapi/openweathermapapi_client.py
openweathermapapi/controllers/__init__.py
openweathermapapi/controllers/base_controller.py
openweathermapapi/controllers/current_weather_data_controller.py
openweathermapapi/exceptions/__init__.py
openweathermapapi/exceptions/api_exception.py
openweathermapapi/http/__init__.py
openweathermapapi/http/http_call_back.py
openweathermapapi/http/http_method_enum.py
openweathermapapi/http/http_request.py
openweathermapapi/http/http_response.py
openweathermapapi/http/auth/__init__.py
openweathermapapi/http/auth/custom_query_authentication.py
openweathermapapi/models/__init__.py
openweathermapapi/models/clouds.py
openweathermapapi/models/coord.py
openweathermapapi/models/main.py
openweathermapapi/models/rain.py
openweathermapapi/models/snow.py
openweathermapapi/models/successful_response.py
openweathermapapi/models/sys.py
openweathermapapi/models/weather.py
openweathermapapi/models/wind.py
openweathermapapi/utilities/__init__.py
openweathermapapi/utilities/file_wrapper.py
open_weather_generated_sdk-2.5.2.dist-info/LICENSE
open_weather_generated_sdk-2.5.2.dist-info/METADATA
open_weather_generated_sdk-2.5.2.dist-info/WHEEL
open_weather_generated_sdk-2.5.2.dist-info/top_level.txt
open_weather_generated_sdk-2.5.2.dist-info/RECORD
